pythetastar/__init__.py
pythetastar/theta_star.py
pythetastar/__pycache__/__init__.cpython-312.pyc
pythetastar/__pycache__/theta_star.cpython-312.pyc
pythetastar-0.0.1.dist-info/LICENSE
pythetastar-0.0.1.dist-info/METADATA
pythetastar-0.0.1.dist-info/WHEEL
pythetastar-0.0.1.dist-info/top_level.txt
pythetastar-0.0.1.dist-info/RECORD
