Metadata-Version: 2.2
Name: pythetastar
Version: 0.0.1
Summary: Implementation of Theta* algorithm
License: MIT License
Project-URL: Homepage, https://github.com/alek5k/pythetastar
Project-URL: Bug Reports, https://github.com/alek5k/pythetastar/issues
Project-URL: Source, https://github.com/alek5k/pythetastar
Classifier: Programming Language :: Python :: 3
Classifier: License :: OSI Approved :: MIT License
Classifier: Operating System :: OS Independent
Requires-Python: >=3.7
License-File: LICENSE
Requires-Dist: numpy
Provides-Extra: dev
Requires-Dist: check-manifest; extra == "dev"
Provides-Extra: test
Requires-Dist: coverage; extra == "test"
